helia_edge/__init__.py
helia_edge/callbacks/__init__.py
helia_edge/callbacks/tqdm_progress_bar.py
helia_edge/converters/__init__.py
helia_edge/converters/cpp/__init__.py
helia_edge/converters/cpp/utils.py
helia_edge/converters/tflite/__init__.py
helia_edge/converters/tflite/converter.py
helia_edge/converters/torch/__init__.py
helia_edge/interpreters/__init__.py
helia_edge/interpreters/tflite/__init__.py
helia_edge/interpreters/tflite/interpreter.py
helia_edge/layers/__init__.py
helia_edge/layers/activations.py
helia_edge/layers/convolutional.py
helia_edge/layers/gumbel_softmax_bottleneck.py
helia_edge/layers/mbconv.py
helia_edge/layers/normalization.py
helia_edge/layers/patching.py
helia_edge/layers/residual_vector_quantizer.py
helia_edge/layers/squeeze_excite.py
helia_edge/layers/vector_quantizer.py
helia_edge/layers/preprocessing/__init__.py
helia_edge/layers/preprocessing/amplitude_warp.py
helia_edge/layers/preprocessing/augmentation_pipeline.py
helia_edge/layers/preprocessing/base_augmentation.py
helia_edge/layers/preprocessing/biquad_filter.py
helia_edge/layers/preprocessing/defines.py
helia_edge/layers/preprocessing/fir_filter.py
helia_edge/layers/preprocessing/frequency_mix_style.py
helia_edge/layers/preprocessing/layer_normalization.py
helia_edge/layers/preprocessing/random_augmentation_pipeline.py
helia_edge/layers/preprocessing/random_background_noises.py
helia_edge/layers/preprocessing/random_channel.py
helia_edge/layers/preprocessing/random_choice.py
helia_edge/layers/preprocessing/random_crop.py
helia_edge/layers/preprocessing/random_cutout.py
helia_edge/layers/preprocessing/random_flip.py
helia_edge/layers/preprocessing/random_gaussian_noise.py
helia_edge/layers/preprocessing/random_noise_distortion.py
helia_edge/layers/preprocessing/random_sine_wave.py
helia_edge/layers/preprocessing/rescaling.py
helia_edge/layers/preprocessing/resizing.py
helia_edge/layers/preprocessing/sine_wave.py
helia_edge/layers/preprocessing/spec_augment.py
helia_edge-0.4.1.dist-info/licenses/LICENSE
helia_edge-0.4.1.dist-info/METADATA
helia_edge-0.4.1.dist-info/WHEEL
helia_edge-0.4.1.dist-info/top_level.txt
helia_edge-0.4.1.dist-info/RECORD
