Metadata-Version: 2.4
Name: helia-edge
Version: 0.4.1
Summary: HeliaEdge is a Keras add-on targeting Ambiq edge AI devices.
Author-email: Ambiq AI <support.aitg@ambiq.com>
Requires-Python: <3.15,>=3.12
License-File: LICENSE
Requires-Dist: h5py>=3.12.1
Requires-Dist: keras>=3.4.0
Requires-Dist: pydantic>=2.8.1
Requires-Dist: requests>=2.32.4
Requires-Dist: tqdm>=4.66.4
Requires-Dist: tensorflow>=2.18.1
Requires-Dist: matplotlib>=3.10.0
Requires-Dist: pandas>=2.3.0
Requires-Dist: scikit-learn>=1.5.2
Requires-Dist: plotly>=5.24.1
Requires-Dist: seaborn>=0.13.2
Requires-Dist: boto3>=1.35.40
Dynamic: license-file
